loraline/__init__.py
loraline/main.py
loraline/controllers/__init__.py
loraline/controllers/base.py
loraline/core/__init__.py
loraline/core/exc.py
loraline/core/version.py
loraline/ext/__init__.py
loraline/plugins/__init__.py
loraline/templates/__init__.py
loraline/templates/introduction.jinja2
loraline/templates/select_host.jinja2
loraline-0.0.1.dev20190804113740.dist-info/LICENSE.md
loraline-0.0.1.dev20190804113740.dist-info/METADATA
loraline-0.0.1.dev20190804113740.dist-info/WHEEL
loraline-0.0.1.dev20190804113740.dist-info/entry_points.txt
loraline-0.0.1.dev20190804113740.dist-info/top_level.txt
loraline-0.0.1.dev20190804113740.dist-info/RECORD
