Metadata-Version: 2.1
Name: loraline
Version: 0.0.1.dev20190804113740
Summary: Loraline configures LoRaWAN transceivers to host devices
Home-page: https://github.com/alexantoniades/loraline
Author: Alexandros Antoniades
Author-email: alex.rogue.antoniades@gmail.com
License: Apache 2.0
Platform: UNKNOWN
